ChaTerminal/__init__.py
ChaTerminal/__main__.py
ChaTerminal/cli.py
cha_terminal/__init__.py
cha_terminal/client.py
cha_terminal/crypto_utils.py
cha_terminal/server.py
cha_terminal/splash.py
chaterminal-1.0.2.dist-info/licenses/LICENSE
chaterminal-1.0.2.dist-info/METADATA
chaterminal-1.0.2.dist-info/WHEEL
chaterminal-1.0.2.dist-info/entry_points.txt
chaterminal-1.0.2.dist-info/top_level.txt
chaterminal-1.0.2.dist-info/RECORD
