Metadata-Version: 2.4
Name: ChaTerminal
Version: 1.0.2
Summary: A terminal-based encrypted chat system for LAN and remote connections
Home-page: https://github.com/Gofaone315/ChaTerminal
Author: Gofaone Tlalang
Author-email: gofaonetlalang@gmail.com
Classifier: Programming Language :: Python :: 3
Classifier: License :: OSI Approved :: MIT License
Classifier: Operating System :: OS Independent
Classifier: Environment :: Console
Classifier: Topic :: Communications :: Chat
Classifier: Topic :: Security :: Cryptography
Requires-Python: >=3.6
License-File: LICENSE
Requires-Dist: colorama
Requires-Dist: pyfiglet
Requires-Dist: pyreadline3; platform_system == "windows"
Dynamic: author
Dynamic: author-email
Dynamic: classifier
Dynamic: description
Dynamic: description-content-type
Dynamic: home-page
Dynamic: license-file
Dynamic: requires-dist
Dynamic: requires-python
Dynamic: summary
